billingyard/__init__.py
billingyard/__main__.py
billingyard/billingyard.py
billingyard/cli.py
billingyard/invoice_processors.py
billingyard/models.py
billingyard/parser.py
billingyard/qrcode_generator.py
billingyard/templates/invoice.html
billingyard/templates/vat_invoice.html
billingyard-1.2.0.dist-info/LICENSE
billingyard-1.2.0.dist-info/METADATA
billingyard-1.2.0.dist-info/WHEEL
billingyard-1.2.0.dist-info/entry_points.txt
billingyard-1.2.0.dist-info/top_level.txt
billingyard-1.2.0.dist-info/RECORD
