Metadata-Version: 2.1
Name: billingyard
Version: 1.2.0
Summary: CLI invoice generator for business entities in the Czech republic
Home-page: https://github.com/MartinVondrak/billing-yard
Author: Martin Vondrák
Author-email: martin@martinvondrak.cz
Keywords: invoice,cli,generator
Classifier: Environment :: Console
Classifier: Intended Audience :: End Users/Desktop
Classifier: License :: OSI Approved :: MIT License
Classifier: Natural Language :: Czech
Classifier: Programming Language :: Python :: 3
Classifier: Topic :: Office/Business :: Financial :: Accounting
Classifier: Development Status :: 5 - Production/Stable
Requires-Python: >=3.9
License-File: LICENSE
Requires-Dist: Click<9,>=8.1.7
Requires-Dist: Jinja2<4,>=3.1.4
Requires-Dist: WeasyPrint<64,>=63.1
Requires-Dist: qrcode<9,>=8.0
